objective_metrics/__init__.py
objective_metrics/modules/__init__.py
objective_metrics/modules/fr_iqa/__init__.py
objective_metrics/modules/fr_iqa/metrics/__init__.py
objective_metrics/modules/fr_iqa/metrics/piqfr.py
objective_metrics/modules/fr_iqa/metrics/pyiqafr.py
objective_metrics/modules/fr_iqa/video.py
objective_metrics/modules/fr_vqa/__init__.py
objective_metrics/modules/fr_vqa/metrics/__init__.py
objective_metrics/modules/fr_vqa/metrics/vmaf.py
objective_metrics/modules/image_features/__init__.py
objective_metrics/modules/image_features/extractors/__init__.py
objective_metrics/modules/image_features/extractors/inception_v3.py
objective_metrics/modules/image_features/extractors/models/__init__.py
objective_metrics/modules/image_features/extractors/models/_inception_v3.py
objective_metrics/modules/image_features/video.py
objective_metrics/modules/nr_iqa/__init__.py
objective_metrics/modules/nr_iqa/metrics/__init__.py
objective_metrics/modules/nr_iqa/metrics/cf.py
objective_metrics/modules/nr_iqa/metrics/koncept512.py
objective_metrics/modules/nr_iqa/metrics/linearity.py
objective_metrics/modules/nr_iqa/metrics/models/__init__.py
objective_metrics/modules/nr_iqa/metrics/models/_cf.py
objective_metrics/modules/nr_iqa/metrics/models/_cf_gpu.py
objective_metrics/modules/nr_iqa/metrics/models/_koncept512.py
objective_metrics/modules/nr_iqa/metrics/models/_linearity.py
objective_metrics/modules/nr_iqa/metrics/models/_si.py
objective_metrics/modules/nr_iqa/metrics/models/_si_gpu.py
objective_metrics/modules/nr_iqa/metrics/models/_spaq.py
objective_metrics/modules/nr_iqa/metrics/models/_unique.py
objective_metrics/modules/nr_iqa/metrics/pyiqa.py
objective_metrics/modules/nr_iqa/metrics/si.py
objective_metrics/modules/nr_iqa/metrics/spaq.py
objective_metrics/modules/nr_iqa/metrics/unique.py
objective_metrics/modules/nr_iqa/metrics/utils/__init__.py
objective_metrics/modules/nr_iqa/metrics/utils/_koncept512.py
objective_metrics-1.2.2.dist-info/LICENSE
objective_metrics-1.2.2.dist-info/METADATA
objective_metrics-1.2.2.dist-info/WHEEL
objective_metrics-1.2.2.dist-info/entry_points.txt
objective_metrics-1.2.2.dist-info/RECORD
