Metadata-Version: 2.1
Name: objective-metrics
Version: 1.2.2
Summary: Command line tool for Image and Video Quality Assessment including MDTVSFA, FAST-VQA, VMAF, MUSIQ and more...
Home-page: https://github.com/bikingSolo/objective-metrics
License: MIT
Keywords: quality assessment,image quality assessment,video quality assessment,pytorch
Author: Lev Borisvoskiy
Author-email: levbor888@gmail.com
Requires-Python: >=3.10,<3.11
Classifier: License :: OSI Approved :: MIT License
Classifier: Programming Language :: Python :: 3
Classifier: Programming Language :: Python :: 3.10
Requires-Dist: ffmpeg-python (>=0.2.0,<0.3.0)
Requires-Dist: gdown (>=5.0.1,<6.0.0)
Requires-Dist: h5py (>=3.10.0,<4.0.0)
Requires-Dist: piq (>=0.8.0,<0.9.0)
Requires-Dist: pyiqa (>=0.1.8,<0.2.0)
Requires-Dist: scikit-video (>=1.1.11,<2.0.0)
Project-URL: Repository, https://github.com/bikingSolo/objective-metrics
